<?xml version="1.0" encoding="UTF-8"?>
<response><status>1</status><count>3</count><info>OK</info><infocode>10000</infocode><tips type="list"><tip><id>B0FFI0BEBV</id><name>果超人</name><district>广东省汕头市金平区</district><adcode>440511</adcode><location>116.715201,23.359440</location><address>金环南路东方中学校门牙外西侧商网铺面第10、11号</address><typecode>050700</typecode><city></city></tip><tip><id>B0FFIZGC52</id><name>果超人</name><district>广东省汕头市龙湖区</district><adcode>440507</adcode><location>116.725526,23.374392</location><address>天山南路天山艺术广场</address><typecode>050300</typecode><city></city></tip><tip><id>B0FFJ1JNBC</id><name>果超人(澄海店)</name><district>广东省汕头市澄海区</district><adcode>440515</adcode><location>116.756124,23.470114</location><address>德政路澄江花园1002幢一层4号之3</address><typecode>050000</typecode><city></city></tip></tips></response>