<?xml version="1.0" encoding="UTF-8"?>
<response><status>1</status><count>10</count><info>OK</info><infocode>10000</infocode><tips type="list"><tip><id>B02F201KQN</id><name>江记庵埠鹅肉饭</name><district>广东省汕头市金平区</district><adcode>440511</adcode><location>116.715678,23.355570</location><address>滨港路14号</address><typecode>050100</typecode><city></city></tip><tip><id>B0FFHNPKYL</id><name>66鹅肉饭</name><district>广东省汕头市澄海区</district><adcode>440515</adcode><location>116.745788,23.466665</location><address>玉亭路下窖路段锦骏馥景园1幢与2幢交界处铺面</address><typecode>050100</typecode><city></city></tip><tip><id>B0FFHRD2UQ</id><name>鹅肉饭店</name><district>广东省汕头市龙湖区</district><adcode>440507</adcode><location>116.764141,23.359067</location><address>长平路与永安汕充公路交界处101号(嘉士楼)</address><typecode>050100</typecode><city></city></tip><tip><id>B0FFHNKMFX</id><name>鹅肉饭</name><district>广东省汕头市金平区</district><adcode>440511</adcode><location>116.668960,23.354815</location><address>升平路与商平路交叉口北100米</address><typecode>050100</typecode><city></city></tip><tip><id>B0FFG82ZIY</id><name>阿雄鹅肉饭</name><district>广东省汕头市潮阳区</district><adcode>440513</adcode><location>116.373397,23.343280</location><address>贵屿镇贵谷公路联堤村委会东北200米</address><typecode>050000</typecode><city></city></tip><tip><id>B0FFIL7MOY</id><name>新溪鹅肉饭(中三合菜市店)</name><district>广东省汕头市龙湖区</district><adcode>440507</adcode><location>116.775759,23.394543</location><address>新溪镇中三合市场西侧铺面</address><typecode>050100</typecode><city></city></tip><tip><id>B02F20O4GJ</id><name>勤业鹅肉饭</name><district>广东省汕头市澄海区</district><adcode>440515</adcode><location>116.759154,23.467765</location><address>泰安路丹霞园6→7号店面</address><typecode>050100</typecode><city></city></tip><tip><id>B0FFIS4X3D</id><name>老牌鹅肉饭</name><district>广东省汕头市澄海区</district><adcode>440515</adcode><location>116.771642,23.451803</location><address>秀夫路3号附近</address><typecode>050100</typecode><city></city></tip><tip><id>B0FFIPG0FW</id><name>老二鹅肉饭</name><district>广东省汕头市金平区</district><adcode>440511</adcode><location>116.713327,23.359755</location><address>公信路金甸园A座109-111房、201-206房</address><typecode>050300</typecode><city></city></tip><tip><id>B0FFJYN1GW</id><name>浮山鹅肉饭</name><district>广东省汕头市龙湖区</district><adcode>440507</adcode><location>116.736740,23.381163</location><address>长江路顺发商行旁</address><typecode>050118</typecode><city></city></tip></tips></response>