<?xml version="1.0" encoding="UTF-8"?>
<response><status>1</status><count>2</count><info>OK</info><infocode>10000</infocode><tips type="list"><tip><id>B0FFJMKRH2</id><name>鮀达联牛肉城</name><district>广东省汕头市金平区</district><adcode>440511</adcode><location>116.698093,23.353149</location><address>石炮台路与红领巾路交叉口南50米</address><typecode>050000</typecode><city></city></tip><tip><id>B0FFIJYS37</id><name>鮀达联牛肉城</name><district>广东省汕头市金平区</district><adcode>440511</adcode><location>116.648010,23.406415</location><address>大学路270号(鮀江加油站隔壁)</address><typecode>050000</typecode><city></city></tip></tips></response>