<?xml version="1.0" encoding="UTF-8"?>
<response><status>1</status><count>2</count><info>OK</info><infocode>10000</infocode><tips type="list"><tip><id>B0FFJOZ932</id><name>佳家超市</name><district>广东省汕头市金平区</district><adcode>440511</adcode><location>116.700001,23.379159</location><address>蛇针路悦泰春天花园9栋号</address><typecode>060000</typecode><city></city></tip><tip><id>B0FFGBJBPZ</id><name>佳家超市(后溪路店)</name><district>广东省汕头市金平区</district><adcode>440511</adcode><location>116.684302,23.385956</location><address>嘉南雅居西南50米(后溪路东)</address><typecode>060200</typecode><city></city></tip></tips></response>