<?xml version="1.0" encoding="UTF-8"?>
<response><status>1</status><count>2</count><info>OK</info><infocode>10000</infocode><tips type="list"><tip><id>B0FFGKV89X</id><name>正元堂筋骨康复馆</name><district>广东省汕头市金平区</district><adcode>440511</adcode><location>116.686126,23.360076</location><address>春杏路23-之101号附近</address><typecode>090601</typecode><city></city></tip><tip><id>B0FFH4K66I</id><name>正元堂筋骨康复馆</name><district>广东省汕头市澄海区</district><adcode>440515</adcode><location>116.770093,23.458931</location><address>中山中路与环城南路交叉口南50米</address><typecode>090000</typecode><city></city></tip></tips></response>