<?xml version="1.0" encoding="UTF-8"?>
<response><status>1</status><count>2</count><info>OK</info><infocode>10000</infocode><tips type="list"><tip><id>B02F20NUIS</id><name>裕丰烟茶酒</name><district>广东省汕头市龙湖区</district><adcode>440507</adcode><location>116.740432,23.356674</location><address>韩江路31号</address><typecode>061210</typecode><city></city></tip><tip><id>B0FFIPKXDN</id><name>裕丰烟茶酒</name><district>广东省汕头市潮阳区</district><adcode>440513</adcode><location>116.482309,23.201889</location><address>237省道西50米</address><typecode>061210</typecode><city></city></tip></tips></response>