<?xml version="1.0" encoding="UTF-8"?>
<response><status>1</status><count>3</count><info>OK</info><infocode>10000</infocode><tips type="list"><tip><id>B0FFIYF4PY</id><name>澳吧乐</name><district>广东省汕头市龙湖区</district><adcode>440507</adcode><location>116.724224,23.377506</location><address>公园路21号长江路23号新一城商业中心负一层卜峰莲花收银道出口</address><typecode>050118</typecode><city></city></tip><tip><id>B0FFK243PL</id><name>奥扒(合胜百货店)</name><district>广东省汕头市龙湖区</district><adcode>440507</adcode><location>116.724378,23.377688</location><address>长江路23号合胜百货5层</address><typecode>050118</typecode><city></city></tip><tip><id>B0FFHE2W6N</id><name>澳霸硅藻泥</name><district>广东省汕头市龙湖区</district><adcode>440507</adcode><location>116.715908,23.386310</location><address>金霞街道高新区科技西路22号第五铺面</address><typecode>060000</typecode><city></city></tip></tips></response>