<?xml version="1.0" encoding="UTF-8"?>
<response><status>1</status><count>2</count><info>OK</info><infocode>10000</infocode><tips type="list"><tip><id>B02F201AOV</id><name>鹤香小食店</name><district>广东省汕头市龙湖区</district><adcode>440507</adcode><location>116.714221,23.374702</location><address>凤凰山路龙湖公寓9栋</address><typecode>050100</typecode><city></city></tip><tip><id>B0FFI5SC4T</id><name>和香小食店</name><district>广东省汕头市潮阳区</district><adcode>440513</adcode><location>116.605912,23.260622</location><address>五举路太和住宅区B4-B5栋东畔铺间7号</address><typecode>050100</typecode><city></city></tip></tips></response>