<?xml version="1.0" encoding="UTF-8"?>
<response><status>1</status><count>10</count><info>OK</info><infocode>10000</infocode><tips type="list"><tip><id>B0FFI6OM43</id><name>老奶奶石磨坊</name><district>广东省汕头市龙湖区</district><adcode>440507</adcode><location>116.730780,23.374120</location><address>衡山路20-24号附近</address><typecode>050100</typecode><city></city></tip><tip><id>B0FFHT5UNV</id><name>老奶奶石磨坊</name><district>广东省汕头市潮阳区</district><adcode>440513</adcode><location>116.408243,23.351625</location><address>御新街与谷贵路交叉口东50米</address><typecode>050000</typecode><city></city></tip><tip><id>B0FFHEWOP4</id><name>老奶奶石磨坊</name><district>广东省汕头市潮阳区</district><adcode>440513</adcode><location>116.351323,23.314529</location><address>蜀蔺饭店斜对面</address><typecode>050000</typecode><city></city></tip><tip><id>B0FFIMK8Z5</id><name>老奶奶石磨坊</name><district>广东省汕头市澄海区</district><adcode>440515</adcode><location>116.778122,23.465643</location><address>东湖市场内第五间店铺</address><typecode>050000</typecode><city></city></tip><tip><id>B0FFG90WL4</id><name>老奶奶石磨坊(环城南路)</name><district>广东省汕头市澄海区</district><adcode>440515</adcode><location>116.768455,23.459959</location><address>环城南路阜阳园7栋一层西5号</address><typecode>050000</typecode><city></city></tip><tip><id>B0FFH3HRP7</id><name>石磨坊</name><district>广东省汕头市龙湖区</district><adcode>440507</adcode><location>116.754302,23.437731</location><address>文祠路与324国道交叉口南150米路西</address><typecode>050000</typecode><city></city></tip><tip><id>B0FFJZH3HG</id><name>老奶奶石磨坊(陈厝合分店)</name><district>广东省汕头市龙湖区</district><adcode>440507</adcode><location>116.743273,23.387439</location><address>黄山路长江医药斜对面</address><typecode>050118</typecode><city></city></tip><tip><id>B0FFG03Q45</id><name>老奶奶石磨坊(光和街)</name><district>广东省汕头市龙湖区</district><adcode>440507</adcode><location>116.740711,23.382127</location><address>新津街道光和街东和1巷9号(陈厝合综合市场附近)</address><typecode>050000</typecode><city></city></tip><tip><id>B0FFFRO6JQ</id><name>老奶奶石磨坊(兴绵街店)</name><district>广东省汕头市龙湖区</district><adcode>440507</adcode><location>116.741526,23.370482</location><address>兴绵街与广兴街交叉口西50米</address><typecode>050000</typecode><city></city></tip><tip><id>B0FFH78S21</id><name>老奶奶石磨坊</name><district>广东省汕头市濠江区</district><adcode>440512</adcode><location>116.729525,23.276161</location><address>青蓝田心宫综合楼一幢底层东起6号</address><typecode>050000</typecode><city></city></tip></tips></response>