<?xml version="1.0" encoding="UTF-8"?>
<response><status>1</status><count>2</count><info>OK</info><infocode>10000</infocode><tips type="list"><tip><id>B02F20O5UA</id><name>麦卡基(黄山路)</name><district>广东省汕头市龙湖区</district><adcode>440507</adcode><location>116.742612,23.388110</location><address>陈暦合泰和街与黄山路交叉口南100米</address><typecode>050300</typecode><city></city></tip><tip><id>B02F20198O</id><name>芳亿茶行</name><district>广东省汕头市龙湖区</district><adcode>440507</adcode><location>116.743747,23.388034</location><address>陈厝合佳和三巷(麦卡基中西餐厅旁)</address><typecode>061200</typecode><city></city></tip></tips></response>