<?xml version="1.0" encoding="UTF-8"?>
<response><status>1</status><count>3</count><info>OK</info><infocode>10000</infocode><tips type="list"><tip><id>B0FFFA2QD8</id><name>王厨出品</name><district>广东省汕头市龙湖区</district><adcode>440507</adcode><location>116.732311,23.367944</location><address>金砂东路与衡山路交界处第一城会所内</address><typecode>050100</typecode><city></city></tip><tip><id>B0FFK5EAED</id><name>养生砂锅粥</name><district>广东省汕头市潮阳区</district><adcode>440513</adcode><location>116.593495,23.251096</location><address>城南一路棉新大道02-03号店,即嘉乐会所隔壁</address><typecode>050000</typecode><city></city></tip><tip><id>B0FFK20VJP</id><name>特色农家菜</name><district>广东省汕头市澄海区</district><adcode>440515</adcode><location>116.751519,23.472833</location><address>玉潭路宜馨花园31幢一层F03号铺面(享乐汇休闲会所对面)</address><typecode>050000</typecode><city></city></tip></tips></response>