<?xml version="1.0" encoding="UTF-8"?>
<response><status>1</status><count>2</count><info>OK</info><infocode>10000</infocode><tips type="list"><tip><id>B0FFJJ5WLJ</id><name>实惠烧烤</name><district>广东省汕头市金平区</district><adcode>440511</adcode><location>116.705009,23.366567</location><address>金砂中路73-75号</address><typecode>050118</typecode><city></city></tip><tip><id>B0FFHQ2CSZ</id><name>实惠烧烤</name><district>广东省汕头市潮南区</district><adcode>440514</adcode><location>116.430938,23.260792</location><address>峡华路504号</address><typecode>050000</typecode><city></city></tip></tips></response>