<?xml version="1.0" encoding="UTF-8"?>
<response><status>1</status><count>2</count><info>OK</info><infocode>10000</infocode><tips type="list"><tip><id>B0FFIV2OVB</id><name>ENGH恩哥意式餐厅(衡山店)</name><district>广东省汕头市龙湖区</district><adcode>440507</adcode><location>116.732544,23.359554</location><address>衡山南路亿兴大厦1层</address><typecode>050205</typecode><city></city></tip><tip><id>B0FFJ3JKXC</id><name>恩哥意式餐厅</name><district>广东省汕头市龙湖区</district><adcode>440507</adcode><location>116.748837,23.366948</location><address>金砂东路星湖商业城4楼</address><typecode>050201</typecode><city></city></tip></tips></response>