<?xml version="1.0" encoding="UTF-8"?>
<response><status>1</status><count>10</count><info>OK</info><infocode>10000</infocode><tips type="list"><tip><id>B02F20OX6F</id><name>牛田洋</name><district>广东省汕头市金平区</district><adcode>440511</adcode><location>116.596140,23.385749</location><address></address><typecode>190108</typecode><city></city></tip><tip><id>B0FFFTANZK</id><name>乐和渔村</name><district>广东省汕头市金平区</district><adcode>440511</adcode><location>116.614294,23.373774</location><address>牛田洋</address><typecode>050119</typecode><city></city></tip><tip><id>B02F20NPUD</id><name>牛田洋</name><district>广东省汕头市濠江区</district><adcode>440512</adcode><location>116.618921,23.327597</location><address></address><typecode>190204</typecode><city></city></tip><tip><id>B0FFG9AEXS</id><name>牛田洋天港农庄</name><district>广东省汕头市金平区</district><adcode>440511</adcode><location>116.619387,23.377619</location><address>071县道</address><typecode>050100</typecode><city></city></tip><tip><id>B0FFFAGV74</id><name>金港渔村餐饮店</name><district>广东省汕头市金平区</district><adcode>440511</adcode><location>116.615457,23.372500</location><address>鮀莲街道天港西牛田洋仔1号</address><typecode>050119</typecode><city></city></tip><tip><id>B02F20NPKG</id><name>天港</name><district>广东省汕头市金平区</district><adcode>440511</adcode><location>116.626202,23.378177</location><address></address><typecode>190108</typecode><city></city></tip><tip><id>B0FFGQFGSE</id><name>牛田洋道路</name><district>广东省汕头市金平区</district><adcode>440511</adcode><location>116.622065,23.385665</location><address></address><typecode>190301</typecode><city></city></tip><tip><id>B0FFI0H7JS</id><name>牛田洋餐室</name><district>广东省汕头市金平区</district><adcode>440511</adcode><location>116.689334,23.359853</location><address>大华路41号东1-4格</address><typecode>050300</typecode><city></city></tip><tip><id>B02F20O4LQ</id><name>牛田洋蟹粥</name><district>广东省汕头市龙湖区</district><adcode>440507</adcode><location>116.730386,23.372022</location><address>珠池路11附近</address><typecode>050100</typecode><city></city></tip><tip><id>B02F20OX4Q</id><name>牛田洋开发区</name><district>广东省汕头市金平区</district><adcode>440511</adcode><location>116.648551,23.358209</location><address></address><typecode>190108</typecode><city></city></tip></tips></response>