<?xml version="1.0" encoding="UTF-8"?>
<response><status>1</status><count>2</count><info>OK</info><infocode>10000</infocode><tips type="list"><tip><id>B0FFHE561K</id><name>李记祖传鱼粥(中山路分店)</name><district>广东省汕头市金平区</district><adcode>440511</adcode><location>116.684327,23.358920</location><address>公园路39号茉莉园北区2幢112房</address><typecode>050100</typecode><city></city></tip><tip><id>B0FFJFOY2P</id><name>李记祖传鱼粥(华山路分店)</name><district>广东省汕头市金平区</district><adcode>440511</adcode><location>116.706869,23.389962</location><address>华山北路98号金禧花园金楠苑103铺</address><typecode>050000</typecode><city></city></tip></tips></response>