<?xml version="1.0" encoding="UTF-8"?>
<response><status>1</status><count>2</count><info>OK</info><infocode>10000</infocode><tips type="list"><tip><id>B02F2004B1</id><name>金苑假日大酒店</name><district>广东省汕头市潮南区</district><adcode>440514</adcode><location>116.411684,23.255327</location><address>峡山广祥路中段</address><typecode>100103</typecode><city></city></tip><tip><id>B0FFIRXGCN</id><name>金苑酒店(铜盂店)</name><district>广东省汕头市潮阳区</district><adcode>440513</adcode><location>116.423771,23.285814</location><address></address><typecode>100000</typecode><city></city></tip></tips></response>