<?xml version="1.0" encoding="UTF-8"?>
<response><status>1</status><count>6</count><info>OK</info><infocode>10000</infocode><tips type="list"><tip><id>B0FFGJ8T6A</id><name>简尚橱柜</name><district>广东省汕头市龙湖区</district><adcode>440507</adcode><location>116.715423,23.380674</location><address>黄河路9号国泰装饰材料城</address><typecode>060000</typecode><city></city></tip><tip><id>B0FFFSEA1K</id><name>简尚</name><district>广东省汕头市金平区</district><adcode>440511</adcode><location>116.691250,23.359087</location><address>中山路与黄岗路交叉口西150米</address><typecode>060000</typecode><city></city></tip><tip><id>B0FFFSO9AX</id><name>简尚</name><district>广东省汕头市濠江区</district><adcode>440512</adcode><location>116.726468,23.277869</location><address>达濠街道永濠街永兴园7栋</address><typecode>061100</typecode><city></city></tip><tip><id>B0FFJWIFCB</id><name>简商店</name><district>广东省汕头市金平区</district><adcode>440511</adcode><location>116.700793,23.362722</location><address>金新南路34-04号附近</address><typecode>060000</typecode><city></city></tip><tip><id>B0FFHR8WUK</id><name>简尚精品服饰</name><district>广东省汕头市潮南区</district><adcode>440514</adcode><location>116.391563,23.263356</location><address>司马浦镇葫芦市大街曼妮芬工业园东北</address><typecode>060000</typecode><city></city></tip><tip><id>B0FFF2M6OI</id><name>简·尚男人生活馆</name><district>广东省汕头市澄海区</district><adcode>440515</adcode><location>116.772470,23.461562</location><address>澄园街行街附属楼15栋</address><typecode>061100</typecode><city></city></tip></tips></response>