<?xml version="1.0" encoding="UTF-8"?>
<response><status>1</status><count>2</count><info>OK</info><infocode>10000</infocode><tips type="list"><tip><id>B0FFGATECH</id><name>跨港通</name><district>广东省汕头市金平区</district><adcode>440511</adcode><location>116.713874,23.366100</location><address>金砂路88号</address><typecode>060000</typecode><city></city></tip><tip><id>B0FFHFF8RV</id><name>跨港通(黄山店)</name><district>广东省汕头市龙湖区</district><adcode>440507</adcode><location>116.747039,23.361471</location><address>金晖北街与黄山路交叉口北100米</address><typecode>060000</typecode><city></city></tip></tips></response>