<?xml version="1.0" encoding="UTF-8"?>
<response><status>1</status><count>7</count><info>OK</info><infocode>10000</infocode><tips type="list"><tip><id>B0FFH53OBZ</id><name>南澳观海公寓</name><district>广东省汕头市南澳县</district><adcode>440523</adcode><location>117.031114,23.414780</location><address>海滨路与龙滨路交汇处南海阁海滨大厦东梯8层802室</address><typecode>100000</typecode><city></city></tip><tip><id>B02F20NUMP</id><name>观海旅馆</name><district>广东省汕头市南澳县</district><adcode>440523</adcode><location>117.029164,23.416152</location><address>后宅镇龙滨路西三巷1号(近龙滨路和海滨路交汇处)</address><typecode>100200</typecode><city></city></tip><tip><id>B0FFIQGZWL</id><name>南澳世纪观海公寓</name><district>广东省汕头市南澳县</district><adcode>440523</adcode><location>117.028013,23.415882</location><address>海滨路世纪大厦13楼</address><typecode>100000</typecode><city></city></tip><tip><id>B0FFI532ZV</id><name>南澳阳光假日观海公寓</name><district>广东省汕头市南澳县</district><adcode>440523</adcode><location>117.028876,23.415873</location><address>海滨路海滨雅园小区1栋1梯403室</address><typecode>100000</typecode><city></city></tip><tip><id>B0FFHR6S1K</id><name>汕头海滨观海公寓</name><district>广东省汕头市南澳县</district><adcode>440523</adcode><location>117.031106,23.415064</location><address>海滨路祥云广场对面国信2期</address><typecode>100100</typecode><city></city></tip><tip><id>B0FFI14NYP</id><name>汕头南澳馆观海公寓国信大厦店</name><district>广东省汕头市南澳县</district><adcode>440523</adcode><location>117.024011,23.416145</location><address>云澳镇海滨路国信大厦欣涛度假村旁</address><typecode>100000</typecode><city></city></tip><tip><id>B0FFI8ZGKU</id><name>汕头南澳岛观海居普通公寓</name><district>广东省汕头市南澳县</district><adcode>440523</adcode><location>117.024068,23.416289</location><address>海滨路26号附近国信海滨花园售楼处后宅镇国信海滨雅园2幢1304房</address><typecode>100000</typecode><city></city></tip></tips></response>