<?xml version="1.0" encoding="UTF-8"?>
<response><status>1</status><count>10</count><info>OK</info><infocode>10000</infocode><tips type="list"><tip><id>B02F20NTTX</id><name>汕头龙光喜来登酒店</name><district>广东省汕头市龙湖区</district><adcode>440507</adcode><location>116.7178,23.35994</location><address>长平路11街区龙光世纪大厦</address><typecode>100102</typecode><city></city></tip><tip><id>B02F20PIF7</id><name>汕头龙光喜来登酒店盛宴标帜餐厅</name><district>广东省汕头市龙湖区</district><adcode>440507</adcode><location>116.718209,23.360160</location><address>长平路11街区龙光喜来登酒店1层</address><typecode>050201</typecode><city></city></tip><tip><id>B0FFFU5GXE</id><name>汕头龙光喜来登酒店停车场</name><district>广东省汕头市龙湖区</district><adcode>440507</adcode><location>116.717652,23.359499</location><address>东方街与金环南路交叉口东200米</address><typecode>150904</typecode><city></city></tip><tip><id>B0FFGLYTRU</id><name>汕头龙光喜来登酒店-室外游泳池</name><district>广东省汕头市龙湖区</district><adcode>440507</adcode><location>116.718220,23.360400</location><address>11街区汕头龙光喜来登酒店5楼</address><typecode>080110</typecode><city></city></tip><tip><id>B0FFGK8ODY</id><name>汕头龙光喜来登酒店-地下停车场</name><district>广东省汕头市龙湖区</district><adcode>440507</adcode><location>116.718544,23.360216</location><address>长平路11街区龙光喜来登酒店(苏宁广场)</address><typecode>150906</typecode><city></city></tip><tip><id>B02F20PIGB</id><name>汕头龙光喜来登酒店采悦轩中餐厅</name><district>广东省汕头市龙湖区</district><adcode>440507</adcode><location>116.718221,23.360393</location><address>长平路11街区龙光世纪大厦龙光喜来登酒店2层</address><typecode>050100</typecode><city></city></tip><tip><id>B0FFGKV7AQ</id><name>汕头龙光喜来登酒店停车场(出入口)</name><district>广东省汕头市龙湖区</district><adcode>440507</adcode><location>116.717720,23.359497</location><address>金环南路9号附近</address><typecode>150909</typecode><city></city></tip><tip><id>B0FFJGYPEO</id><name>龙光喜来登酒店大堂吧</name><district>广东省汕头市龙湖区</district><adcode>440507</adcode><location>116.717449,23.360218</location><address>11街区龙光世纪大厦龙光喜来登酒店内(近林百欣会展中心)</address><typecode>050500</typecode><city></city></tip><tip><id>B0FFHRG2OJ</id><name>龙光喜来登酒店行政酒廊</name><district>广东省汕头市龙湖区</district><adcode>440507</adcode><location>116.717910,23.360056</location><address>长平路11街区龙光喜来登酒店23层</address><typecode>080304</typecode><city></city></tip><tip><id>B0FFIXLR5M</id><name>龙光喜来登酒店盛宴标帜餐厅</name><district>广东省汕头市金平区</district><adcode>440511</adcode><location>116.699231,23.368649</location><address>金美花园西北</address><typecode>050201</typecode><city></city></tip></tips></response>