<?xml version="1.0" encoding="UTF-8"?>
<response><status>1</status><count>2</count><info>OK</info><infocode>10000</infocode><tips type="list"><tip><id>B0FFG16HSG</id><name>桃园公寓</name><district>广东省汕头市潮南区</district><adcode>440514</adcode><location>116.316593,23.276373</location><address>中华街东100米</address><typecode>120302</typecode><city></city></tip><tip><id>B0FFI2VA5W</id><name>汕头桃园公寓</name><district>广东省汕头市潮南区</district><adcode>440514</adcode><location>116.375756,23.254651</location><address>司马浦镇美佳惠超市旁(国道324南200米)</address><typecode>120302</typecode><city></city></tip></tips></response>