<?xml version="1.0" encoding="UTF-8"?>
<response><status>1</status><count>4</count><info>OK</info><infocode>10000</infocode><tips type="list"><tip><id>B0FFG03BJW</id><name>兴业水果店(兴业路店)</name><district>广东省汕头市金平区</district><adcode>440511</adcode><location>116.710006,23.371986</location><address>兴业路与龙眼北路交叉口西100米</address><typecode>060704</typecode><city></city></tip><tip><id>B0FFIIJYH8</id><name>立兴水果店</name><district>广东省汕头市金平区</district><adcode>440511</adcode><location>116.710700,23.371917</location><address>兴业路与龙眼北路交叉口东50米</address><typecode>060704</typecode><city></city></tip><tip><id>B0FFJOZ94F</id><name>晨通果蔬店</name><district>广东省汕头市金平区</district><adcode>440511</adcode><location>116.706714,23.371989</location><address>兴业路14号1座105</address><typecode>060000</typecode><city></city></tip><tip><id>B02F2018Q1</id><name>丹喜面包(兴业店)</name><district>广东省汕头市金平区</district><adcode>440511</adcode><location>116.710700,23.372145</location><address>龙眼北路玫瑰园41幢</address><typecode>050800</typecode><city></city></tip></tips></response>